telegraph/__init__.py
telegraph/__main__.py
telegraph/cli.py
telegraph/config/__init__.py
telegraph/config/app_settings.py
telegraph/config/smtp_settings.py
telegraph/main.py
telegraph/models/__init__.py
telegraph/models/emails.py
telegraph/models/templating.py
telegraph/util/__init__.py
telegraph/util/app_setup.py
telegraph/util/file_handling.py
telegraph/util/pipeline_base.py
telegraph/util/template_handling.py
telegraph_emails-0.1.0.dist-info/METADATA
telegraph_emails-0.1.0.dist-info/WHEEL
telegraph_emails-0.1.0.dist-info/entry_points.txt
telegraph_emails-0.1.0.dist-info/RECORD
