Metadata-Version: 2.3
Name: telegraph-emails
Version: 0.1.0
Summary: 
Author: Alex
Author-email: aswann@protonmail.com
Requires-Python: >=3.12
Classifier: Programming Language :: Python :: 3
Classifier: Programming Language :: Python :: 3.12
Classifier: Programming Language :: Python :: 3.13
Requires-Dist: coverage (>=7.8.0,<8.0.0)
Requires-Dist: html2text (>=2025.4.15,<2026.0.0)
Requires-Dist: hypothesis (>=6.131.9,<7.0.0)
Requires-Dist: jinja2 (>=3.1.6,<4.0.0)
Requires-Dist: openpyxl (>=3.1.5,<4.0.0)
Requires-Dist: pandas (>=2.2.3,<3.0.0)
Requires-Dist: pandas-stubs (>=2.2.3.250308,<3.0.0.0)
Requires-Dist: pydantic (>=2.11.4,<3.0.0)
Requires-Dist: pydantic-settings[yaml] (>=2.9.1,<3.0.0)
Requires-Dist: pytest (>=8.3.5,<9.0.0)
Requires-Dist: typer (>=0.15.3,<0.16.0)
Requires-Dist: types-pyyaml (>=6.0.12.20250402,<7.0.0.0)
